LICENSE
MANIFEST.in
README.md
setup.py
Shosetsu/Parsing.py
Shosetsu/VNDB.py
Shosetsu/__init__.py
Shosetsu/errors.py
Shosetsu.egg-info/PKG-INFO
Shosetsu.egg-info/SOURCES.txt
Shosetsu.egg-info/dependency_links.txt
Shosetsu.egg-info/requires.txt
Shosetsu.egg-info/top_level.txt