Metadata-Version: 1.1
Name: Shosetsu
Version: 1.1.2
Summary: Python 3 Aiohttp VNDB Scraper
Home-page: https://github.com/ccubed/Shosetsu
Author: Cooper Click
Author-email: ccubed.techno@gmail.com
License: MIT
Keywords: VNDB asyncio aiohttp scraping
Platform: UNKNOWN
Classifier: Development Status :: 4 - Beta
Classifier: Intended Audience :: Developers
Classifier: License :: OSI Approved :: MIT License
Classifier: Programming Language :: Python :: 3.5
Classifier: Programming Language :: Python :: 3 :: Only
Classifier: Topic :: Software Development :: Libraries
